{
    "results": [
                    
        {
            "name": "Atalaias",
            "lat": 39.76581476600271,
            "long": -7.874554256675542
        },
        {
            "name": "Brasilia",
            "lat": -47.91814590668119,
            "long": -15.82714789793406
        },
                   
        {
            "name": "Carregais",
            "lat": 39.76144239290572,
            "long": -7.758138184982122
        },
        {
            "name": "Carregal",
            "lat": 39.76801388500655,
            "long": -7.762512077661656
        },
        {
            "name": "Casal da Ribeira",
            "lat": 39.7930667840174,
            "long": -7.758291659403652
        },
        {
            "name": "Casalinho",
            "lat": 39.78022297187869,
            "long": -7.757641019252778
        },
        {
            "name": "Castanheira",
            "lat": 39.79772933949717,
            "long": -7.878814460560417
        },
        {
            "name": "Castelo Branco",
            "lat": 39.8162319446091,
            "long": -7.493923567810046
        },
       
        {
            "name": "Cerejeira",
            "lat": 39.81433081722575,
            "long": -7.755046753101116
        },
        {
            "name": "Chão do Galego",
            "lat": 39.77408724340044,
            "long": -7.785624243405019
        },
        {
            "name": "Cunqueiros",
            "lat": 39.81472716543299,
            "long": -7.840467994337315
        },
        {
            "name": "Dáspera",
            "lat": 39.85661136731704 ,
            "long": -7.781663888754796
        },
       
        {
            "name": "Ferraria",
            "lat": 39.78749429930757,
            "long": -7.776891683186401
        },
              
        {
            "name": "Genebra",
            "lat": 46.20900413370136,
            "long": 6.165162428530946
        },
        {
            "name": "Giesteiras",
            "lat": 39.77408724340044,
            "long": -7.785624243405019
        },
        {
            "name": "Herdade",
            "lat": 39.84639882845775,
            "long": -7.810793227184533
        },
        {
            "name": "Lameira",
            "lat": 39.77945207584094,
            "long": -7.771603475534604
        }
        ,
        {
            "name": "Lisboa",
            "lat": 38.72528541402597,
            "long": -9.14685354464363
        },
        
        {
            "name": "Madrid",
            "lat": 40.41622842075002,
            "long": -3.70165169887577
        },
        
        {
            "name": "Serra de S.Mamede",
            "lat": 39.3080159347044,
            "long": -7.393538207931403
        },
              
        {
            "name": "Moitas",
            "lat": 39.73257485380321,
            "long": -7.860938307984904
        },
        
        {
            "name": "Montes da Senhora",
            "lat": 39.77539499338536,
            "long": -7.803328527594319
        },
              
        {
            "name": "Oleiros",
            "lat": 39.91560987225428,
            "long": -7.903705986567292
        },
        
        {
            "name": "Pedra do Altar",
            "lat": 39.71044052139389,
            "long": -7.817403225374672
        },
    
        {
            "name": "Peral",
            "lat": 39.69098750366553,
            "long": -7.801522084538188
        },
                     
        {
            "name": "Portalegre",
            "lat": 39.29691253701744,
            "long": -7.42649181799155
        },
              
        {
            "name": "Proença-a-Nova",
            "lat": 39.75077601900526,
            "long": -7.919389907933881
        },
        
        {
            "name": "Ribeira do Alvito",
            "lat": 39.77628709921572,
            "long": -7.694318872835023
        },
        
        {
            "name": "Rio Ocreza",
            "lat": 39.77548479069063,
            "long": -7.733570379237812
        },
        
        {
            "name": "Ripanso",
            "lat": 39.76441362468206,
            "long": -7.834388996446147
        },
        
        {
            "name": "S.Pedro do Esteval",
            "lat": 39.63620216619318,
            "long": -7.843579561696487
        },
        
        {
            "name": "Serra da Estrela",
            "lat": 40.32313078857225,
            "long": -7.612667431766074
        },
        
        {
            "name": "Serra da Gardunha",
            "lat": 40.16940489864764,
            "long": -7.382259599641763
        },
        
        {
            "name": "Serra da Gata",
            "lat": 40.15884098748148,
            "long": -6.748823139238794
        },
        {
            "name": "Serra de S.Mamede",
            "lat": 39.3080159347044,
            "long": -7.393538207931403
        },
        {
            "name": "Serra do Vergão",
            "lat": 39.75153773493862,
            "long": -7.995107054368659
        },
        {
            "name": "Sobrainho dos Gaios",
            "lat": 39.82933283935308,
            "long": -7.744848834533865
        },
        {
            "name": "Sobreira Formosa",
            "lat": 39.77131976756416,
            "long": -7.840406038039224
        },
        {
            "name": "Vale Clérigo",
            "lat": 39.7124115483142,
            "long": -7.827641179237312
        },
        {
            "name": "Vale da Ursa",
            "lat": 39.8058763206685,
            "long": -7.870976587938506
        },
        {
            "name": "Vales",
            "lat": 39.80728952570032,
            "long": -7.79306236323626
        },
        {
            "name": "Vila Velha de Rodão",
            "lat": 39.65903223835951,
            "long": -7.667703152275973
        }
    ]
}
        
            


        
    
